setup.py
pyhexad/__init__.py
pyhexad/config.py
pyhexad/file_helpers.py
pyhexad/h5_helpers.py
pyhexad/h5appendRows.py
pyhexad/h5getInfo.py
pyhexad/h5newArray.py
pyhexad/h5newFile.py
pyhexad/h5newGroup.py
pyhexad/h5newTable.py
pyhexad/h5readArray.py
pyhexad/h5readAttribute.py
pyhexad/h5readImage.py
pyhexad/h5readTable.py
pyhexad/h5showList.py
pyhexad/h5showTree.py
pyhexad/h5writeArray.py
pyhexad/h5writeAttribute.py
pyhexad/h5writeTable.py
pyhexad/pyxll_extension.py
pyhexad/renderer.py
pyhexad/shape_helpers.py
pyhexad/table_helpers.py
pyhexad/type_helpers.py
pyhexad.egg-info/PKG-INFO
pyhexad.egg-info/SOURCES.txt
pyhexad.egg-info/dependency_links.txt
pyhexad.egg-info/top_level.txt