Metadata-Version: 1.1
Name: pyhexad
Version: 0.1.5
Summary: An HDF5 Excel add-in using PyXLL
Home-page: http://www.hdfgroup.org/
Author: The HDF Group, Enthought Inc.
Author-email: gheber@hdfgroup.org, dpinte@enthought.com
License: BSD
Keywords: excel hdf5 pyxll
Platform: UNKNOWN
Classifier: Development Status :: 4 - Beta
Classifier: License :: OSI Approved :: BSD License
Classifier: Programming Language :: Python :: 2.7
